algo/__init__.py
algo/arraylib.py
algo/treelib.py
cahap/__init__.py
phap/__init__.py
phapbm/__init__.py
stralgo/__init__.py
stralgo/base.py
stralgo/json.py
stralgo/hash/__init__.py
stralgo/hash/sha.py
stralgo/hash/sm/__init__.py
stralgo/hash/sm/sm3libs.py
phap-3.1.0.dist-info/LICENSE
phap-3.1.0.dist-info/METADATA
phap-3.1.0.dist-info/WHEEL
phap-3.1.0.dist-info/top_level.txt
phap-3.1.0.dist-info/RECORD
