Metadata-Version: 2.1
Name: phap
Version: 3.1.0
Summary: Programing Helpful Algorithm Package
Home-page: https://github.com/DashBing/phap/
Author: DashBing
Author-email: mcbbkf@outlook.com
Project-URL: Github, https://github.com/DashBing/phap/
Project-URL: Old Project Version(stralgo), https://pypi.org/project/stralgo/
Classifier: Development Status :: 5 - Production/Stable
Classifier: Programming Language :: Python :: Implementation :: CPython
Classifier: Programming Language :: Python :: 3.11
Classifier: License :: OSI Approved :: MIT License
Classifier: Operating System :: OS Independent
Classifier: Natural Language :: English
Classifier: Natural Language :: Chinese (Simplified)
Requires-Python: >=3.9
License-File: LICENSE
